{
  "resourceType": "CodeSystem",
  "id": "hl7-administrative-gender",
  "url": "https://termgit.elga.gv.at/CodeSystem/hl7-administrative-gender",
  "identifier": [
    {
      "use": "official",
      "system": "urn:ietf:rfc:3986",
      "value": "urn:oid:2.16.840.1.113883.5.1"
    }
  ],
  "version": "1.0.0+20230131",
  "name": "hl7-administrative-gender",
  "title": "HL7 Administrative Gender",
  "status": "retired",
  "date": "2023-06-30",
  "content": "complete",
  "count": 3,
  "concept": [
    {
      "code": "F",
      "display": "Female",
      "designation": [
        {
          "language": "de-AT",
          "value": "Weiblich"
        }
      ]
    },
    {
      "code": "M",
      "display": "Male",
      "designation": [
        {
          "language": "de-AT",
          "value": "M\u00e4nnlich"
        }
      ]
    },
    {
      "code": "UN",
      "display": "Undifferentiated",
      "designation": [
        {
          "language": "de-AT",
          "value": "Divers"
        }
      ]
    }
  ]
}